README.md
setup.py
easy_to_cython/__init__.py
easy_to_cython/action.py
easy_to_cython/build.py
easy_to_cython.egg-info/PKG-INFO
easy_to_cython.egg-info/SOURCES.txt
easy_to_cython.egg-info/dependency_links.txt
easy_to_cython.egg-info/entry_points.txt
easy_to_cython.egg-info/requires.txt
easy_to_cython.egg-info/top_level.txt