Metadata-Version: 2.1
Name: easy-to-cython
Version: 1.0.0
Summary: Simple and easy to packages code replace cython
Home-page: https://github.com/pypa/sampleproject
Author: Elijah
Author-email: 610152942@qq.com
License: MIT
Platform: UNKNOWN
Classifier: Programming Language :: Python :: 3
Classifier: License :: OSI Approved :: MIT License
Classifier: Operating System :: OS Independent
Requires-Python: >=3.6
